{
    "status": 3,
    "startTimes": [
        1,
        17,
        14,
        30,
        998,
        60,
        45,
        555,
        117,
        105,
        908,
        798,
        89,
        75,
        1012,
        91,
        933,
        297,
        946,
        844,
        1054,
        258,
        959,
        135,
        216,
        252,
        128,
        692,
        304,
        713,
        150,
        1069,
        209,
        165,
        1084,
        1099,
        180,
        651,
        360,
        195,
        1026,
        330,
        226,
        240,
        896,
        600,
        775,
        285,
        515,
        1114,
        787,
        271,
        1129,
        348,
        735,
        750,
        495,
        615,
        1144,
        722,
        856,
        315,
        452,
        883,
        972,
        509,
        682,
        577,
        540,
        343,
        672,
        765,
        477,
        529,
        1159,
        822,
        810,
        921,
        1040,
        392,
        569,
        589,
        376,
        702,
        388,
        405,
        449,
        420,
        1174,
        435,
        630,
        642,
        661,
        483,
        834,
        1189,
        465,
        869,
        1204,
        985
    ],
    "objectiveValue": 25885.0,
    "solverRuntimeInMilliseconds": 4,
    "optional": {}
}