{
    "status": 3,
    "startTimes": [
        1130,
        4,
        600,
        490,
        15,
        280,
        741,
        30,
        990,
        615,
        259,
        695,
        75,
        37,
        105,
        118,
        123,
        52,
        135,
        660,
        949,
        90,
        1005,
        176,
        60,
        815,
        962,
        1145,
        1032,
        575,
        648,
        210,
        544,
        719,
        567,
        195,
        936,
        674,
        638,
        165,
        976,
        150,
        753,
        183,
        849,
        225,
        794,
        628,
        1047,
        289,
        240,
        1020,
        1160,
        272,
        862,
        256,
        765,
        479,
        733,
        300,
        524,
        315,
        780,
        407,
        449,
        805,
        345,
        827,
        1175,
        1060,
        686,
        885,
        555,
        330,
        1075,
        510,
        1088,
        840,
        899,
        912,
        706,
        498,
        1102,
        373,
        360,
        376,
        1190,
        420,
        1205,
        1116,
        461,
        435,
        924,
        872,
        537,
        404,
        390,
        1220,
        586,
        467
    ],
    "objectiveValue": 29603.0,
    "solverRuntimeInMilliseconds": 4,
    "optional": {}
}