{
    "status": 3,
    "startTimes": [
        652,
        3,
        13,
        5,
        19,
        30,
        31,
        45,
        390,
        57,
        596,
        105,
        62,
        81,
        77,
        93,
        66,
        75,
        450,
        90,
        809,
        700,
        739,
        212,
        303,
        101,
        185,
        118,
        121,
        563,
        136,
        150,
        135,
        142,
        225,
        168,
        713,
        290,
        360,
        344,
        468,
        164,
        609,
        574,
        180,
        230,
        181,
        195,
        753,
        270,
        630,
        202,
        210,
        767,
        516,
        211,
        409,
        824,
        781,
        795,
        258,
        318,
        534,
        242,
        839,
        248,
        619,
        854,
        255,
        543,
        350,
        869,
        274,
        488,
        287,
        374,
        480,
        285,
        500,
        308,
        420,
        329,
        427,
        641,
        884,
        664,
        317,
        726,
        508,
        335,
        437,
        458,
        585,
        553,
        382,
        526,
        899,
        676,
        688,
        405
    ],
    "objectiveValue": 16457.0,
    "solverRuntimeInMilliseconds": 4,
    "optional": {}
}