{
    "status": 3,
    "startTimes": [
        2,
        15,
        1164,
        45,
        30,
        78,
        89,
        60,
        75,
        198,
        1079,
        105,
        240,
        118,
        152,
        135,
        1240,
        1049,
        1258,
        150,
        229,
        675,
        182,
        1150,
        141,
        166,
        480,
        179,
        195,
        1185,
        213,
        1290,
        291,
        1110,
        217,
        884,
        319,
        975,
        255,
        253,
        300,
        270,
        990,
        277,
        313,
        334,
        336,
        825,
        347,
        358,
        404,
        394,
        414,
        420,
        430,
        1199,
        493,
        513,
        462,
        470,
        447,
        810,
        900,
        840,
        1005,
        518,
        504,
        1214,
        535,
        530,
        565,
        552,
        855,
        870,
        547,
        707,
        1019,
        605,
        589,
        578,
        594,
        1064,
        1124,
        642,
        649,
        914,
        1275,
        1035,
        634,
        662,
        929,
        656,
        1305,
        1094,
        689,
        703,
        959,
        944,
        1138,
        721
    ],
    "objectiveValue": 17538.0,
    "solverRuntimeInMilliseconds": 5,
    "optional": {}
}