{
    "status": 3,
    "startTimes": [
        13,
        26,
        12,
        22,
        49,
        579,
        41,
        448,
        1154,
        66,
        1215,
        1275,
        1185,
        61,
        165,
        302,
        195,
        250,
        64,
        325,
        82,
        1364,
        79,
        273,
        1080,
        463,
        97,
        1303,
        96,
        258,
        604,
        687,
        717,
        645,
        267,
        221,
        231,
        353,
        1319,
        702,
        181,
        180,
        240,
        388,
        566,
        1335,
        333,
        363,
        1289,
        226,
        1200,
        479,
        631,
        659,
        210,
        618,
        1094,
        1349,
        492,
        1110,
        246,
        1395,
        517,
        436,
        286,
        530,
        316,
        291,
        1230,
        283,
        1035,
        309,
        376,
        1125,
        542,
        554,
        673,
        1380,
        1260,
        476,
        498,
        1140,
        343,
        434,
        1170,
        1005,
        1050,
        356,
        411,
        1244,
        1020,
        511,
        422,
        378,
        400,
        460,
        593,
        1065,
        414,
        399
    ],
    "objectiveValue": 29726.0,
    "solverRuntimeInMilliseconds": 7,
    "optional": {}
}