{
    "status": 3,
    "startTimes": [
        2,
        15,
        740,
        34,
        121,
        540,
        28,
        27,
        47,
        50,
        1298,
        63,
        48,
        1124,
        1184,
        789,
        1313,
        559,
        729,
        1270,
        72,
        226,
        120,
        1200,
        801,
        184,
        605,
        211,
        175,
        1065,
        671,
        150,
        1284,
        135,
        165,
        816,
        243,
        232,
        202,
        682,
        168,
        629,
        216,
        1079,
        531,
        189,
        195,
        276,
        1094,
        715,
        263,
        1035,
        705,
        612,
        1257,
        1169,
        495,
        249,
        1230,
        692,
        578,
        752,
        260,
        1328,
        550,
        517,
        524,
        623,
        312,
        289,
        272,
        297,
        1005,
        595,
        642,
        292,
        1245,
        313,
        336,
        329,
        588,
        569,
        391,
        328,
        663,
        335,
        1109,
        388,
        764,
        511,
        1020,
        650,
        1050,
        374,
        775,
        477,
        1214,
        1154,
        505,
        1139
    ],
    "objectiveValue": 29434.0,
    "solverRuntimeInMilliseconds": 6,
    "optional": {}
}