{
    "status": 3,
    "startTimes": [
        8,
        45,
        22,
        1000,
        70,
        56,
        103,
        117,
        85,
        435,
        647,
        193,
        197,
        244,
        288,
        540,
        274,
        164,
        527,
        158,
        150,
        469,
        128,
        269,
        516,
        209,
        1015,
        829,
        214,
        445,
        624,
        179,
        281,
        453,
        330,
        345,
        610,
        508,
        788,
        375,
        449,
        229,
        803,
        360,
        812,
        315,
        1030,
        583,
        497,
        483,
        405,
        487,
        986,
        552,
        348,
        420,
        588,
        853,
        388,
        468,
        392,
        559,
        440,
        958,
        614,
        654,
        724,
        633,
        669,
        781,
        757,
        506,
        568,
        1388,
        734,
        596,
        572,
        944,
        604,
        703,
        667,
        773,
        718,
        890,
        741,
        826,
        765,
        916,
        929,
        683,
        865,
        751,
        710,
        1045,
        702,
        877,
        687,
        903,
        972,
        844
    ],
    "objectiveValue": 11380.0,
    "solverRuntimeInMilliseconds": 41741,
    "optional": {}
}