{
    "numOperations": 100,
    "releaseTimes": [
        13,
        14,
        21,
        27,
        45,
        49,
        55,
        58,
        79,
        79,
        85,
        88,
        89,
        95,
        96,
        115,
        124,
        126,
        130,
        157,
        160,
        165,
        175,
        180,
        181,
        193,
        193,
        197,
        201,
        201,
        201,
        212,
        212,
        216,
        221,
        227,
        231,
        235,
        246,
        259,
        259,
        261,
        270,
        276,
        276,
        281,
        291,
        293,
        296,
        297,
        301,
        302,
        305,
        308,
        312,
        312,
        317,
        317,
        317,
        325,
        326,
        348,
        357,
        361,
        372,
        380,
        389,
        399,
        401,
        408,
        413,
        428,
        428,
        428,
        428,
        436,
        443,
        444,
        476,
        478,
        479,
        479,
        482,
        482,
        487,
        492,
        496,
        499,
        519,
        523,
        523,
        526,
        532,
        553,
        556,
        556,
        569,
        570,
        574,
        580
    ],
    "dueDates": [
        78,
        98,
        67,
        59,
        96,
        61,
        93,
        140,
        128,
        134,
        98,
        183,
        118,
        161,
        147,
        177,
        215,
        165,
        187,
        215,
        228,
        191,
        203,
        254,
        212,
        213,
        288,
        236,
        267,
        221,
        269,
        232,
        284,
        276,
        303,
        314,
        255,
        300,
        330,
        277,
        329,
        262,
        325,
        316,
        345,
        339,
        330,
        343,
        301,
        336,
        317,
        364,
        313,
        329,
        345,
        345,
        368,
        334,
        348,
        388,
        355,
        400,
        432,
        439,
        428,
        413,
        415,
        428,
        415,
        444,
        465,
        448,
        487,
        448,
        498,
        486,
        449,
        488,
        560,
        535,
        492,
        553,
        565,
        548,
        530,
        556,
        521,
        518,
        590,
        530,
        580,
        556,
        572,
        613,
        618,
        617,
        599,
        639,
        594,
        670
    ],
    "processingTimes": [
        11,
        10,
        11,
        6,
        9,
        1,
        8,
        5,
        14,
        11,
        6,
        14,
        11,
        9,
        3,
        1,
        13,
        10,
        11,
        10,
        7,
        6,
        3,
        1,
        9,
        4,
        14,
        11,
        10,
        5,
        3,
        10,
        5,
        6,
        7,
        14,
        11,
        10,
        12,
        2,
        15,
        1,
        15,
        7,
        9,
        2,
        7,
        15,
        4,
        8,
        5,
        11,
        2,
        13,
        3,
        9,
        12,
        11,
        8,
        1,
        12,
        3,
        7,
        1,
        8,
        14,
        14,
        15,
        13,
        11,
        6,
        13,
        2,
        4,
        5,
        10,
        5,
        12,
        4,
        14,
        5,
        15,
        12,
        10,
        8,
        10,
        2,
        6,
        7,
        3,
        4,
        5,
        6,
        9,
        5,
        11,
        10,
        5,
        5,
        13
    ],
    "powerConsumptions": [
        7.961564799620917,
        7.6113340217825879,
        8.248638303204487,
        6.404645867518378,
        6.755174868165408,
        76.56262547762197,
        12.0747637266318,
        19.299887917696514,
        2.477090543849115,
        7.110605186142888,
        15.632360394806853,
        5.225484813723185,
        7.195707475107457,
        8.047528179759058,
        21.98875860546832,
        92.9979739483415,
        3.372655275730451,
        4.4336358831960969,
        3.408988949850415,
        6.366992423822653,
        4.765234613334093,
        10.835116382619125,
        31.595616512059505,
        64.71111010853312,
        8.071776475080583,
        9.842062183872516,
        6.389150679745214,
        7.882472040376836,
        8.297752045734706,
        6.235251291239519,
        12.031272192102227,
        9.929901287303002,
        7.14025285746081,
        15.207987913834307,
        8.514834862809395,
        6.142761028232188,
        3.42501356498145,
        7.1209979238292739,
        6.084313123802978,
        42.24064450654447,
        4.7148190037803439,
        76.2766387695437,
        3.903822896647654,
        9.570702437927514,
        6.495436378779971,
        23.59206788557612,
        5.521688475344957,
        5.233063138342131,
        23.897065985081605,
        8.81595218280603,
        16.22498926053908,
        3.0162131271294987,
        21.612582398784605,
        4.27830317296163,
        18.51394011822566,
        3.6065711218808285,
        4.553943633802796,
        3.145761540107713,
        7.3414765820151619,
        77.1940701268444,
        7.393679431724395,
        30.261961603291053,
        10.343527597187294,
        52.14487296527618,
        4.732108929578322,
        3.1811366991775249,
        3.5811988066541566,
        2.04543523180858,
        3.6650526734835746,
        7.824079112113941,
        15.735394971840896,
        6.601935076683115,
        34.38604746734279,
        9.831572191469843,
        9.542251420426945,
        9.46787894249223,
        18.83394910905074,
        4.037890185051853,
        15.207698972605402,
        2.3030819357263927,
        16.042267645802,
        6.408587794571465,
        7.401945555453509,
        5.293397109948804,
        9.825880932532395,
        3.319463639754609,
        22.78261924008481,
        13.715669438984213,
        10.033324057236588,
        12.056442358357283,
        10.004559815618807,
        7.14943057559821,
        15.868541927606272,
        8.447471442506084,
        12.678907950097877,
        4.979657458462425,
        4.133432600032582,
        15.957104301600547,
        18.760931985719993,
        2.836038652902619
    ],
    "maxDeviation": 0,
    "numMeteringIntervals": 300,
    "lengthMeteringInterval": 15,
    "maxEnergyConsumptions": [
        100.0,
        100.0,
        100.0,
        100.0,
        100.0,
        100.0,
        100.0,
        100.0,
        100.0,
        100.0,
        100.0,
        100.0,
        100.0,
        100.0,
        100.0,
        100.0,
        100.0,
        100.0,
        100.0,
        100.0,
        100.0,
        100.0,
        100.0,
        100.0,
        100.0,
        100.0,
        100.0,
        100.0,
        100.0,
        100.0,
        100.0,
        100.0,
        100.0,
        100.0,
        100.0,
        100.0,
        100.0,
        100.0,
        100.0,
        100.0,
        100.0,
        100.0,
        100.0,
        100.0,
        100.0,
        100.0,
        100.0,
        100.0,
        100.0,
        100.0,
        100.0,
        100.0,
        100.0,
        100.0,
        100.0,
        100.0,
        100.0,
        100.0,
        100.0,
        100.0,
        100.0,
        100.0,
        100.0,
        100.0,
        100.0,
        100.0,
        100.0,
        100.0,
        100.0,
        100.0,
        100.0,
        100.0,
        100.0,
        100.0,
        100.0,
        100.0,
        100.0,
        100.0,
        100.0,
        100.0,
        100.0,
        100.0,
        100.0,
        100.0,
        100.0,
        100.0,
        100.0,
        100.0,
        100.0,
        100.0,
        100.0,
        100.0,
        100.0,
        100.0,
        100.0,
        100.0,
        100.0,
        100.0,
        100.0,
        100.0,
        100.0,
        100.0,
        100.0,
        100.0,
        100.0,
        100.0,
        100.0,
        100.0,
        100.0,
        100.0,
        100.0,
        100.0,
        100.0,
        100.0,
        100.0,
        100.0,
        100.0,
        100.0,
        100.0,
        100.0,
        100.0,
        100.0,
        100.0,
        100.0,
        100.0,
        100.0,
        100.0,
        100.0,
        100.0,
        100.0,
        100.0,
        100.0,
        100.0,
        100.0,
        100.0,
        100.0,
        100.0,
        100.0,
        100.0,
        100.0,
        100.0,
        100.0,
        100.0,
        100.0,
        100.0,
        100.0,
        100.0,
        100.0,
        100.0,
        100.0,
        100.0,
        100.0,
        100.0,
        100.0,
        100.0,
        100.0,
        100.0,
        100.0,
        100.0,
        100.0,
        100.0,
        100.0,
        100.0,
        100.0,
        100.0,
        100.0,
        100.0,
        100.0,
        100.0,
        100.0,
        100.0,
        100.0,
        100.0,
        100.0,
        100.0,
        100.0,
        100.0,
        100.0,
        100.0,
        100.0,
        100.0,
        100.0,
        100.0,
        100.0,
        100.0,
        100.0,
        100.0,
        100.0,
        100.0,
        100.0,
        100.0,
        100.0,
        100.0,
        100.0,
        100.0,
        100.0,
        100.0,
        100.0,
        100.0,
        100.0,
        100.0,
        100.0,
        100.0,
        100.0,
        100.0,
        100.0,
        100.0,
        100.0,
        100.0,
        100.0,
        100.0,
        100.0,
        100.0,
        100.0,
        100.0,
        100.0,
        100.0,
        100.0,
        100.0,
        100.0,
        100.0,
        100.0,
        100.0,
        100.0,
        100.0,
        100.0,
        100.0,
        100.0,
        100.0,
        100.0,
        100.0,
        100.0,
        100.0,
        100.0,
        100.0,
        100.0,
        100.0,
        100.0,
        100.0,
        100.0,
        100.0,
        100.0,
        100.0,
        100.0,
        100.0,
        100.0,
        100.0,
        100.0,
        100.0,
        100.0,
        100.0,
        100.0,
        100.0,
        100.0,
        100.0,
        100.0,
        100.0,
        100.0,
        100.0,
        100.0,
        100.0,
        100.0,
        100.0,
        100.0,
        100.0,
        100.0,
        100.0,
        100.0,
        100.0,
        100.0,
        100.0,
        100.0,
        100.0,
        100.0,
        100.0,
        100.0,
        100.0,
        100.0,
        100.0,
        100.0,
        100.0,
        100.0,
        100.0,
        100.0,
        100.0,
        100.0,
        100.0,
        100.0,
        100.0,
        100.0,
        100.0,
        100.0,
        100.0,
        100.0,
        100.0,
        100.0,
        100.0,
        100.0,
        100.0,
        100.0
    ],
    "metadata": {}
}