{
    "status": 3,
    "startTimes": [
        59,
        7,
        102,
        87,
        149,
        163,
        176,
        190,
        63,
        72,
        171,
        52,
        110,
        222,
        121,
        287,
        226,
        283,
        237,
        264,
        342,
        360,
        398,
        441,
        317,
        374,
        416,
        302,
        388,
        431,
        541,
        456,
        615,
        480,
        457,
        526,
        504,
        459,
        661,
        520,
        719,
        746,
        540,
        675,
        567,
        556,
        595,
        689,
        624,
        803,
        645,
        759,
        840,
        876,
        952,
        646,
        774,
        824,
        903,
        854,
        660,
        978,
        992,
        1009,
        868,
        888,
        964,
        734,
        767,
        1062,
        1171,
        944,
        1179,
        1095,
        1124,
        1005,
        1076,
        1108,
        1230,
        1166,
        1215,
        1138,
        1047,
        1141,
        1143,
        1236,
        1305,
        1332,
        1347,
        1239,
        1357,
        1282,
        1254,
        1440,
        1371,
        1329,
        1314,
        1383,
        1454,
        1424
    ],
    "objectiveValue": 44697.0,
    "solverRuntimeInMilliseconds": 0,
    "optional": {}
}