{
    "status": 3,
    "startTimes": [
        0,
        13,
        942,
        955,
        47,
        100,
        26,
        75,
        554,
        84,
        42,
        275,
        534,
        155,
        226,
        718,
        269,
        60,
        1110,
        106,
        165,
        132,
        695,
        254,
        186,
        116,
        223,
        673,
        179,
        288,
        209,
        140,
        346,
        765,
        798,
        880,
        837,
        434,
        413,
        357,
        425,
        199,
        381,
        240,
        778,
        661,
        900,
        731,
        823,
        302,
        334,
        621,
        630,
        1140,
        327,
        405,
        568,
        1155,
        653,
        600,
        316,
        524,
        705,
        367,
        473,
        886,
        927,
        914,
        1057,
        391,
        479,
        1025,
        543,
        854,
        751,
        808,
        511,
        578,
        862,
        642,
        459,
        1037,
        1066,
        1125,
        1080,
        784,
        1095,
        445,
        453,
        745,
        998,
        494,
        1014,
        483,
        681,
        608,
        969,
        504,
        986,
        590
    ],
    "objectiveValue": 28340.0,
    "solverRuntimeInMilliseconds": 1996,
    "optional": {}
}