{
    "status": 3,
    "startTimes": [
        118,
        179,
        15,
        185,
        282,
        200,
        103,
        227,
        165,
        420,
        143,
        327,
        131,
        92,
        354,
        215,
        369,
        197,
        166,
        300,
        390,
        345,
        448,
        554,
        405,
        479,
        565,
        429,
        266,
        465,
        325,
        657,
        501,
        640,
        538,
        255,
        702,
        746,
        315,
        492,
        761,
        824,
        687,
        516,
        597,
        620,
        933,
        899,
        710,
        673,
        853,
        870,
        583,
        613,
        793,
        723,
        945,
        1065,
        990,
        734,
        1079,
        1107,
        910,
        836,
        805,
        1000,
        1170,
        1138,
        1093,
        1155,
        1049,
        962,
        920,
        977,
        885,
        1182,
        1019,
        1273,
        956,
        1122,
        1247,
        1398,
        1033,
        1194,
        1372,
        1357,
        1235,
        1214,
        1205,
        1312,
        1425,
        1454,
        1297,
        1349,
        1390,
        1230,
        1260,
        1412,
        1469,
        1284
    ],
    "objectiveValue": 24912.0,
    "solverRuntimeInMilliseconds": 0,
    "optional": {}
}