{
    "status": 3,
    "startTimes": [
        29,
        15,
        5,
        60,
        372,
        537,
        75,
        66,
        45,
        650,
        61,
        110,
        161,
        504,
        765,
        87,
        177,
        99,
        221,
        1305,
        554,
        91,
        118,
        138,
        738,
        838,
        794,
        158,
        1335,
        132,
        196,
        229,
        726,
        208,
        151,
        592,
        615,
        311,
        541,
        189,
        753,
        258,
        175,
        246,
        625,
        194,
        1320,
        579,
        291,
        779,
        572,
        484,
        1380,
        215,
        242,
        684,
        241,
        287,
        305,
        410,
        423,
        808,
        467,
        1399,
        261,
        269,
        711,
        1365,
        307,
        354,
        386,
        281,
        1350,
        301,
        323,
        388,
        558,
        522,
        424,
        336,
        602,
        662,
        329,
        437,
        458,
        361,
        343,
        823,
        1280,
        371,
        640,
        401,
        697,
        447,
        499,
        480,
        403,
        673,
        518,
        444
    ],
    "objectiveValue": 23038.0,
    "solverRuntimeInMilliseconds": 56994,
    "optional": {}
}