{
    "status": 3,
    "startTimes": [
        13,
        66,
        99,
        50,
        86,
        113,
        166,
        129,
        151,
        140,
        255,
        225,
        282,
        270,
        178,
        210,
        195,
        328,
        349,
        236,
        315,
        374,
        300,
        435,
        377,
        344,
        495,
        362,
        393,
        449,
        521,
        407,
        418,
        510,
        476,
        460,
        614,
        645,
        538,
        585,
        629,
        564,
        599,
        551,
        691,
        655,
        667,
        704,
        784,
        719,
        745,
        688,
        729,
        777,
        873,
        808,
        870,
        823,
        855,
        797,
        893,
        901,
        763,
        915,
        1106,
        1124,
        1059,
        1007,
        932,
        837,
        990,
        958,
        1127,
        975,
        1160,
        930,
        1045,
        1140,
        1093,
        1079,
        1031,
        1185,
        1241,
        1200,
        1289,
        1215,
        1271,
        1259,
        1319,
        1221,
        1348,
        1304,
        1405,
        1333,
        1416,
        1364,
        1380,
        1454,
        1438,
        1395
    ],
    "objectiveValue": 31850.0,
    "solverRuntimeInMilliseconds": 0,
    "optional": {}
}