{
    "status": 3,
    "startTimes": [
        285,
        357,
        78,
        149,
        326,
        458,
        67,
        375,
        190,
        204,
        450,
        130,
        254,
        344,
        605,
        656,
        236,
        702,
        177,
        165,
        808,
        473,
        222,
        795,
        300,
        690,
        390,
        579,
        827,
        314,
        841,
        945,
        270,
        405,
        418,
        968,
        674,
        596,
        854,
        886,
        555,
        1078,
        495,
        777,
        509,
        725,
        525,
        645,
        628,
        434,
        540,
        1047,
        930,
        982,
        1170,
        1148,
        745,
        759,
        876,
        1064,
        1093,
        1016,
        911,
        1257,
        1495,
        955,
        1034,
        1272,
        1316,
        1450,
        1211,
        1244,
        1228,
        1526,
        1298,
        1192,
        1350,
        1121,
        1425,
        1408,
        1135,
        1364,
        1541,
        1392,
        1376,
        1634,
        1605,
        1331,
        1555,
        1710,
        1652,
        1482,
        1675,
        1440,
        1723,
        1511,
        1579,
        1693,
        1619,
        1469
    ],
    "objectiveValue": 39802.0,
    "solverRuntimeInMilliseconds": 0,
    "optional": {}
}