{
    "status": 3,
    "startTimes": [
        0,
        15,
        97,
        325,
        522,
        36,
        30,
        1050,
        32,
        70,
        911,
        50,
        91,
        1005,
        53,
        79,
        59,
        133,
        67,
        289,
        108,
        388,
        443,
        857,
        140,
        623,
        303,
        122,
        483,
        130,
        1123,
        153,
        870,
        157,
        399,
        192,
        410,
        309,
        583,
        555,
        172,
        541,
        173,
        176,
        188,
        334,
        208,
        213,
        926,
        598,
        1140,
        1065,
        229,
        246,
        254,
        221,
        206,
        239,
        883,
        224,
        237,
        260,
        479,
        455,
        1155,
        284,
        1080,
        608,
        377,
        268,
        516,
        502,
        576,
        968,
        1185,
        897,
        280,
        351,
        1020,
        467,
        362,
        421,
        1200,
        323,
        1093,
        343,
        562,
        990,
        372,
        347,
        833,
        498,
        1108,
        535,
        360,
        820,
        432,
        1035,
        845,
        1170
    ],
    "objectiveValue": 20531.0,
    "solverRuntimeInMilliseconds": 8,
    "optional": {}
}