{
    "status": 3,
    "startTimes": [
        1,
        16,
        35,
        30,
        48,
        61,
        79,
        75,
        91,
        135,
        105,
        115,
        123,
        148,
        121,
        161,
        239,
        172,
        183,
        207,
        191,
        279,
        251,
        264,
        196,
        349,
        339,
        361,
        217,
        308,
        225,
        318,
        291,
        328,
        417,
        299,
        388,
        481,
        441,
        402,
        431,
        617,
        381,
        375,
        457,
        558,
        685,
        543,
        522,
        668,
        468,
        477,
        698,
        531,
        495,
        779,
        496,
        510,
        630,
        740,
        603,
        595,
        573,
        586,
        582,
        952,
        832,
        645,
        661,
        651,
        770,
        966,
        682,
        878,
        854,
        937,
        724,
        713,
        755,
        735,
        825,
        765,
        929,
        795,
        1006,
        980,
        810,
        1058,
        1020,
        920,
        846,
        863,
        912,
        994,
        889,
        1044,
        877,
        904,
        897,
        1032
    ],
    "objectiveValue": 1055.0,
    "solverRuntimeInMilliseconds": 4,
    "optional": {}
}