{
    "status": 3,
    "startTimes": [
        15,
        44,
        33,
        730,
        89,
        59,
        75,
        419,
        494,
        313,
        553,
        102,
        120,
        360,
        285,
        584,
        135,
        163,
        216,
        809,
        1229,
        148,
        1242,
        330,
        1120,
        299,
        194,
        180,
        210,
        404,
        254,
        1076,
        1134,
        825,
        346,
        1057,
        1371,
        535,
        689,
        228,
        522,
        240,
        334,
        434,
        447,
        1312,
        855,
        269,
        1356,
        465,
        634,
        509,
        375,
        389,
        1142,
        1298,
        959,
        1270,
        1177,
        1189,
        794,
        675,
        1069,
        1047,
        1215,
        1037,
        778,
        1088,
        569,
        750,
        973,
        647,
        1202,
        870,
        915,
        599,
        1154,
        614,
        719,
        480,
        1020,
        1165,
        1097,
        928,
        840,
        899,
        1256,
        701,
        1029,
        1284,
        885,
        629,
        660,
        1341,
        984,
        764,
        942,
        1326,
        1003,
        1110
    ],
    "objectiveValue": 31565.0,
    "solverRuntimeInMilliseconds": 17022,
    "optional": {}
}