{
    "status": 3,
    "startTimes": [
        99,
        8,
        13,
        28,
        112,
        60,
        180,
        125,
        74,
        149,
        160,
        268,
        222,
        193,
        312,
        276,
        336,
        175,
        449,
        374,
        252,
        240,
        462,
        434,
        346,
        412,
        390,
        293,
        494,
        403,
        480,
        522,
        554,
        324,
        569,
        721,
        637,
        540,
        510,
        673,
        684,
        612,
        706,
        658,
        544,
        782,
        817,
        600,
        630,
        699,
        771,
        832,
        749,
        757,
        795,
        929,
        841,
        807,
        969,
        897,
        1027,
        1087,
        1003,
        911,
        1017,
        920,
        1082,
        1138,
        944,
        997,
        984,
        1181,
        1200,
        1168,
        1216,
        1123,
        1154,
        1287,
        1255,
        1110,
        1275,
        1071,
        1065,
        1320,
        1332,
        1204,
        1243,
        1279,
        1407,
        1205,
        1421,
        1369,
        1346,
        1479,
        1360,
        1305,
        1442,
        1499,
        1383,
        1433
    ],
    "objectiveValue": 46671.0,
    "solverRuntimeInMilliseconds": 0,
    "optional": {}
}